{"format":2,"version":"7.2.7","globals":"ba8197f646cf5ad573c6c506a982c556","files":{"d_627bb1e7b9621b0a___init___py":{"hash":"37078612bd7eeb4210b6242cda2ac19a","index":{"nums":[0,1,0,0,0,0,0,0],"html_filename":"d_627bb1e7b9621b0a___init___py.html","relative_filename":"src\\airtable_to_sqlite\\__init__.py"}},"d_627bb1e7b9621b0a___main___py":{"hash":"34110382afed94b04b7a656cc074e140","index":{"nums":[0,1,3,3,0,0,0,0],"html_filename":"d_627bb1e7b9621b0a___main___py.html","relative_filename":"src\\airtable_to_sqlite\\__main__.py"}},"d_0c18da857d182d42___init___py":{"hash":"84959d5452f56131fe734209f5d192cf","index":{"nums":[0,1,25,0,0,18,0,0],"html_filename":"d_0c18da857d182d42___init___py.html","relative_filename":"src\\airtable_to_sqlite\\cli\\__init__.py"}},"d_627bb1e7b9621b0a_constants_py":{"hash":"82911f915ec6d4eb178851af621afbce","index":{"nums":[0,1,10,0,0,0,0,0],"html_filename":"d_627bb1e7b9621b0a_constants_py.html","relative_filename":"src\\airtable_to_sqlite\\constants.py"}},"d_627bb1e7b9621b0a_main_py":{"hash":"1c1fc4c3f4a964c4e076dd47f29842f2","index":{"nums":[0,1,127,12,0,44,0,0],"html_filename":"d_627bb1e7b9621b0a_main_py.html","relative_filename":"src\\airtable_to_sqlite\\main.py"}},"d_627bb1e7b9621b0a_schema_py":{"hash":"7f06debde203f6f8709f44d9871f4321","index":{"nums":[0,1,76,0,0,42,0,0],"html_filename":"d_627bb1e7b9621b0a_schema_py.html","relative_filename":"src\\airtable_to_sqlite\\schema.py"}},"d_a44f0ac069e85531___init___py":{"hash":"37078612bd7eeb4210b6242cda2ac19a","index":{"nums":[0,1,0,0,0,0,0,0],"html_filename":"d_a44f0ac069e85531___init___py.html","relative_filename":"tests\\__init__.py"}},"d_a44f0ac069e85531_conftest_py":{"hash":"7b30f6fd2b5a563920f1b13b2860bb45","index":{"nums":[0,1,16,0,0,6,0,0],"html_filename":"d_a44f0ac069e85531_conftest_py.html","relative_filename":"tests\\conftest.py"}},"d_a44f0ac069e85531_dummy_returns_py":{"hash":"9512f439dc294e895875fddf83970168","index":{"nums":[0,1,3,0,0,0,0,0],"html_filename":"d_a44f0ac069e85531_dummy_returns_py.html","relative_filename":"tests\\dummy_returns.py"}},"d_a44f0ac069e85531_test_cli_py":{"hash":"b79709a38f9effe5f583aea04b8fd488","index":{"nums":[0,1,24,0,0,6,0,0],"html_filename":"d_a44f0ac069e85531_test_cli_py.html","relative_filename":"tests\\test_cli.py"}},"d_a44f0ac069e85531_test_main_py":{"hash":"068acf8fdf77529efc96c53203f3f340","index":{"nums":[0,1,88,0,0,12,0,0],"html_filename":"d_a44f0ac069e85531_test_main_py.html","relative_filename":"tests\\test_main.py"}},"d_a44f0ac069e85531_test_schema_py":{"hash":"bd9da951d05b98e326cf16c8b26baec5","index":{"nums":[0,1,53,0,0,0,0,0],"html_filename":"d_a44f0ac069e85531_test_schema_py.html","relative_filename":"tests\\test_schema.py"}}}}