{".class":"MypyFile","_fullname":"pycounts_ng24.pycounts_ng24","future_import_flags":[],"is_partial_stub_package":false,"is_stub":false,"names":{".class":"SymbolTable","Counter":{".class":"SymbolTableNode","cross_ref":"collections.Counter","kind":"Gdef"},"__annotations__":{".class":"SymbolTableNode","kind":"Gdef","node":{".class":"Var","flags":["is_ready"],"fullname":"pycounts_ng24.pycounts_ng24.__annotations__","name":"__annotations__","type":{".class":"Instance","args":["builtins.str",{".class":"AnyType","missing_import_name":null,"source_any":null,"type_of_any":6}],"type_ref":"builtins.dict"}}},"__doc__":{".class":"SymbolTableNode","kind":"Gdef","node":{".class":"Var","flags":["is_ready"],"fullname":"pycounts_ng24.pycounts_ng24.__doc__","name":"__doc__","type":"builtins.str"}},"__file__":{".class":"SymbolTableNode","kind":"Gdef","node":{".class":"Var","flags":["is_ready"],"fullname":"pycounts_ng24.pycounts_ng24.__file__","name":"__file__","type":"builtins.str"}},"__name__":{".class":"SymbolTableNode","kind":"Gdef","node":{".class":"Var","flags":["is_ready"],"fullname":"pycounts_ng24.pycounts_ng24.__name__","name":"__name__","type":"builtins.str"}},"__package__":{".class":"SymbolTableNode","kind":"Gdef","node":{".class":"Var","flags":["is_ready"],"fullname":"pycounts_ng24.pycounts_ng24.__package__","name":"__package__","type":"builtins.str"}},"clean_text":{".class":"SymbolTableNode","kind":"Gdef","node":{".class":"FuncDef","abstract_status":0,"arg_kinds":[0],"arg_names":["text"],"dataclass_transform_spec":null,"flags":[],"fullname":"pycounts_ng24.pycounts_ng24.clean_text","name":"clean_text","type":null}},"count_words":{".class":"SymbolTableNode","kind":"Gdef","node":{".class":"FuncDef","abstract_status":0,"arg_kinds":[0],"arg_names":["input_file"],"dataclass_transform_spec":null,"flags":[],"fullname":"pycounts_ng24.pycounts_ng24.count_words","name":"count_words","type":null}},"load_text":{".class":"SymbolTableNode","kind":"Gdef","node":{".class":"FuncDef","abstract_status":0,"arg_kinds":[0],"arg_names":["input_file"],"dataclass_transform_spec":null,"flags":[],"fullname":"pycounts_ng24.pycounts_ng24.load_text","name":"load_text","type":null}},"punctuation":{".class":"SymbolTableNode","cross_ref":"string.punctuation","kind":"Gdef"}},"path":"/Users/nasim/Desktop/block4/524/pycounts_ng24/src/pycounts_ng24/pycounts_ng24.py"}